seamm_geometric/__init__.py
seamm_geometric/_version.py
seamm_geometric/py.typed
seamm_geometric/seamm_geometric.py
seamm_geometric/data/README.md
seamm_geometric/data/look_and_say.dat
seamm_geometric/data/references.bib
seamm_geometric-2025.5.7.dist-info/licenses/LICENSE.txt
tests/__init__.py
tests/test_seamm_geometric.py
seamm_geometric-2025.5.7.dist-info/METADATA
seamm_geometric-2025.5.7.dist-info/WHEEL
seamm_geometric-2025.5.7.dist-info/top_level.txt
seamm_geometric-2025.5.7.dist-info/RECORD
