Metadata-Version: 2.4
Name: seamm_geometric
Version: 2025.5.7
Summary: geomeTRIC connector for SEAMM
Author-email: Paul Saxe <psaxe@vt.edu>
License: MIT
Project-URL: Source, https://github.com/molssi-seamm/seamm_geometric/
Project-URL: Documentation, https://molssi-seamm.github.io/seamm_geometric/
Classifier: License :: OSI Approved :: MIT License
Classifier: Programming Language :: Python :: 3
Requires-Python: >=3.8
License-File: LICENSE.txt
Requires-Dist: bibtexparser
Requires-Dist: geometric
Requires-Dist: importlib-resources
Requires-Dist: numpy
Requires-Dist: seamm-util
Requires-Dist: tabulate
Provides-Extra: test
Requires-Dist: pytest>=6.1.2; extra == "test"
Dynamic: license-file
